README.md
setup.py
trader/__init__.py
trader/__main__.py
trader/general.py
trader/_args/__init__.py
trader/_args/argument.py
trader/_args/basic.py
trader/_contract/IERC20.py
trader/_contract/MailboxFacet.py
trader/_contract/MuteSwitchRouterDynamic.py
trader/_contract/__init__.py
trader/_utils/__init__.py
trader/common/__init__.py
trader/common/_command.py
trader/common/account.py
trader/common/test.py
trader/eth/__init__.py
trader/eth/_command.py
trader/eth/balance.py
trader/eth/wei.py
trader/zksync/__init__.py
trader/zksync/_command.py
trader/zksync/balance.py
trader/zksync/transfer.py
trader/zksync/withdraw.py
trader_client_kit.egg-info/PKG-INFO
trader_client_kit.egg-info/SOURCES.txt
trader_client_kit.egg-info/dependency_links.txt
trader_client_kit.egg-info/entry_points.txt
trader_client_kit.egg-info/requires.txt
trader_client_kit.egg-info/top_level.txt
trader_client_kit.egg-info/zip-safe