Metadata-Version: 2.1
Name: trader-client-kit
Version: 0.3.1
Summary: Trader - a common tool for blockchain
Home-page: UNKNOWN
Author: remy
Author-email: remy.ace@outlook.com
License: MIT License
Keywords: trader-cli
Platform: UNKNOWN
Classifier: Programming Language :: Python :: 3
Classifier: Operating System :: OS Independent
Classifier: Development Status :: 1 - Planning
Classifier: Topic :: Utilities
